{
  "timestamp": "2025-12-26T20:20:06.148265",
  "period_hours": 24,
  "total_trades": 34,
  "win_rate": 14.705882352941178,
  "total_pnl_pct": -7.117450542804508,
  "best_direction": "SHORT",
  "recommended_config": {
    "allowed_directions": [
      "SHORT"
    ],
    "six_dim_min_score_to_trade": 6,
    "recommended_hold_time_sec": 269,
    "contextual_mode": true,
    "min_confidence": 0.3,
    "generated_at": "2025-12-26T20:20:06.148253",
    "based_on_trades": 34
  },
  "analysis_summary": "\n回測分析結果 (24h)\n========================\n總交易: 34 筆\n總 PnL: -7.12%\n\nLONG 表現:\n  - 交易數: 23\n  - 勝率: 13.0%\n  - PnL: -2.52%\n\nSHORT 表現:\n  - 交易數: 11\n  - 勝率: 18.2%\n  - PnL: -4.60%\n\n推薦方向: SHORT\n"
}