{
  "timestamp": "2025-12-30T05:22:58.782526",
  "period_hours": 24,
  "total_trades": 917,
  "win_rate": 38.276990185387135,
  "total_pnl_pct": -43.781756156424066,
  "best_direction": "SHORT",
  "recommended_config": {
    "allowed_directions": [
      "SHORT"
    ],
    "six_dim_min_score_to_trade": 6,
    "recommended_hold_time_sec": 26,
    "contextual_mode": true,
    "min_confidence": 0.3,
    "generated_at": "2025-12-30T05:22:58.782490",
    "based_on_trades": 917
  },
  "analysis_summary": "\n回測分析結果 (24h)\n========================\n總交易: 917 筆\n總 PnL: -43.78%\n\nLONG 表現:\n  - 交易數: 457\n  - 勝率: 39.2%\n  - PnL: -13.33%\n\nSHORT 表現:\n  - 交易數: 460\n  - 勝率: 37.4%\n  - PnL: -30.45%\n\n推薦方向: SHORT\n"
}