{
  "timestamp": "2025-12-20T00:44:51.582318",
  "period_hours": 24,
  "total_trades": 1594,
  "win_rate": 10.28858218318695,
  "total_pnl_pct": -554.030514689647,
  "best_direction": "LONG",
  "recommended_config": {
    "allowed_directions": [
      "LONG"
    ],
    "six_dim_min_score_to_trade": 6,
    "recommended_hold_time_sec": 6,
    "contextual_mode": true,
    "min_confidence": 0.3,
    "generated_at": "2025-12-20T00:44:51.582258",
    "based_on_trades": 1594
  },
  "analysis_summary": "\n回測分析結果 (24h)\n========================\n總交易: 1594 筆\n總 PnL: -554.03%\n\nLONG 表現:\n  - 交易數: 735\n  - 勝率: 10.1%\n  - PnL: -293.16%\n\nSHORT 表現:\n  - 交易數: 859\n  - 勝率: 10.5%\n  - PnL: -260.88%\n\n推薦方向: LONG\n"
}