{
  "timestamp": "2025-12-27T08:04:37.836550",
  "period_hours": 24,
  "total_trades": 555,
  "win_rate": 47.387387387387385,
  "total_pnl_pct": 33.284587382197884,
  "best_direction": "SHORT",
  "recommended_config": {
    "allowed_directions": [
      "SHORT"
    ],
    "six_dim_min_score_to_trade": 6,
    "recommended_hold_time_sec": 43,
    "contextual_mode": true,
    "min_confidence": 0.3,
    "generated_at": "2025-12-27T08:04:37.836525",
    "based_on_trades": 555
  },
  "analysis_summary": "\n回測分析結果 (24h)\n========================\n總交易: 555 筆\n總 PnL: 33.28%\n\nLONG 表現:\n  - 交易數: 277\n  - 勝率: 46.6%\n  - PnL: 13.27%\n\nSHORT 表現:\n  - 交易數: 278\n  - 勝率: 48.2%\n  - PnL: 20.01%\n\n推薦方向: SHORT\n"
}