{
  "timestamp": "2025-12-19T23:33:46.347024",
  "period_hours": 24,
  "total_trades": 175,
  "win_rate": 45.714285714285715,
  "total_pnl_pct": 336.41615787108907,
  "best_direction": "SHORT",
  "recommended_config": {
    "allowed_directions": [
      "SHORT"
    ],
    "six_dim_min_score_to_trade": 6,
    "recommended_hold_time_sec": 6,
    "contextual_mode": true,
    "min_confidence": 0.3,
    "generated_at": "2025-12-19T23:33:46.346988",
    "based_on_trades": 175
  },
  "analysis_summary": "\n回測分析結果 (24h)\n========================\n總交易: 175 筆\n總 PnL: 336.42%\n\nLONG 表現:\n  - 交易數: 79\n  - 勝率: 50.6%\n  - PnL: 128.15%\n\nSHORT 表現:\n  - 交易數: 96\n  - 勝率: 41.7%\n  - PnL: 208.26%\n\n推薦方向: SHORT\n"
}