{
  "timestamp": "2025-12-15T13:27:12.687621",
  "period_hours": 24,
  "total_trades": 938,
  "win_rate": 19.936034115138593,
  "total_pnl_pct": 15.25887582814078,
  "best_direction": "LONG",
  "recommended_config": {
    "allowed_directions": [
      "LONG"
    ],
    "six_dim_min_score_to_trade": 6,
    "recommended_hold_time_sec": 8,
    "contextual_mode": true,
    "min_confidence": 0.3,
    "generated_at": "2025-12-15T13:27:12.687588",
    "based_on_trades": 938
  },
  "analysis_summary": "\n回測分析結果 (24h)\n========================\n總交易: 938 筆\n總 PnL: 15.26%\n\nLONG 表現:\n  - 交易數: 468\n  - 勝率: 20.9%\n  - PnL: 10.66%\n\nSHORT 表現:\n  - 交易數: 470\n  - 勝率: 18.9%\n  - PnL: 4.60%\n\n推薦方向: LONG\n"
}